pale_exe/__init__.py
pale_exe/pale_exe.py
p_exe-0.1.1.dist-info/METADATA
p_exe-0.1.1.dist-info/WHEEL
p_exe-0.1.1.dist-info/top_level.txt
p_exe-0.1.1.dist-info/RECORD
