Metadata-Version: 2.1
Name: p-exe
Version: 0.1.1
Requires-Python: >=3.7
Requires-Dist: maturin >=1.7.0
